spotify/__init__.py
spotify/client.py
spotify/errors.py
spotify/http.py
spotify/models/__init__.py
spotify/models/album.py
spotify/models/artist.py
spotify/models/copyright.py
spotify/models/followers.py
spotify/models/image.py
spotify/models/paging.py
spotify/models/track.py
spotify/models/abc/__init__.py
spotify/models/abc/base.py
spotify/models/abc/baseAlbum.py
spotify/models/abc/baseArtist.py
spotify/models/abc/baseTrack.py
spotify/models/abc/object.py
spotify/models/abc/restriction.py
spotify/models/extras/__init__.py
spotify/models/extras/externalID.py
spotify/models/extras/externalURL.py
spotify/models/simple/__init__.py
spotify/models/simple/simplifiedAlbum.py
spotify/models/simple/simplifiedArtist.py
spotify/models/simple/simplifiedTrack.py
spyotipy-0.1a0.dist-info/LICENSE
spyotipy-0.1a0.dist-info/METADATA
spyotipy-0.1a0.dist-info/WHEEL
spyotipy-0.1a0.dist-info/top_level.txt
spyotipy-0.1a0.dist-info/RECORD
