Metadata-Version: 2.1
Name: spyotipy
Version: 0.1a0
Summary: A Python wrapper for the Spotify API
Home-page: https://github.com/mohamed040406/spyotipy
Author: mohamed040406
License: MIT
Project-URL: Documentation, https://spyotipy.readthedocs.io/en/latest/
Project-URL: Issue tracker, https://github.com/mohamed040406/spyotipy/issues
Platform: UNKNOWN
Classifier: Programming Language :: Python
Classifier: Programming Language :: Python :: 3.7
Classifier: Programming Language :: Python :: 3.8
Classifier: Programming Language :: Python :: 3.9
Classifier: License :: OSI Approved :: MIT License
Classifier: Intended Audience :: Developers
Classifier: Natural Language :: English
Classifier: Topic :: Software Development :: Libraries
Classifier: Topic :: Software Development :: Libraries :: Python Modules
Requires-Python: >=3.7
Requires-Dist: aiohttp (==3.7.3)
Provides-Extra: docs
Requires-Dist: sphinx (==3.0.3) ; extra == 'docs'
Requires-Dist: sphinxcontrib-trio (==1.1.2) ; extra == 'docs'
Requires-Dist: sphinxcontrib-websupport ; extra == 'docs'
